{
    "home-manager": {
        "branch": "release-23.11",
        "description": "Manage a user environment using Nix  [maintainer=@rycee] ",
        "homepage": "https://nix-community.github.io/home-manager/",
        "owner": "nix-community",
        "repo": "home-manager",
        "rev": "ab5542e9dbd13d0100f8baae2bc2d68af901f4b4",
        "sha256": "1pikl3ai9if1lp2zllxpdnp2krkgqsbrry6f9b4gsxh60jnamyy0",
        "type": "tarball",
        "url": "https://github.com/nix-community/home-manager/archive/ab5542e9dbd13d0100f8baae2bc2d68af901f4b4.tar.gz",
        "url_template": "https://github.com/<owner>/<repo>/archive/<rev>.tar.gz"
    },
    "niv": {
        "branch": "master",
        "description": "Easy dependency management for Nix projects",
        "homepage": "https://github.com/nmattia/niv",
        "owner": "nmattia",
        "repo": "niv",
        "rev": "5f0defe2f71020812e39a51dab68a64fb293ace1",
        "sha256": "12wscam2163pirzbmz0pw6cmnn6xa0dy8ax5kxi5bgxcp728vxyd",
        "type": "tarball",
        "url": "https://github.com/nmattia/niv/archive/5f0defe2f71020812e39a51dab68a64fb293ace1.tar.gz",
        "url_template": "https://github.com/<owner>/<repo>/archive/<rev>.tar.gz"
    },
    "nixos-hardware": {
        "branch": "master",
        "description": "A collection of NixOS modules covering hardware quirks.",
        "homepage": "",
        "owner": "NixOS",
        "repo": "nixos-hardware",
        "rev": "d9e0b26202fd500cf3e79f73653cce7f7d541191",
        "sha256": "1dk5m5ksvalw6gs30npvgw20zb6iyy3m5qn8iidcps96gq3bab8l",
        "type": "tarball",
        "url": "https://github.com/NixOS/nixos-hardware/archive/d9e0b26202fd500cf3e79f73653cce7f7d541191.tar.gz",
        "url_template": "https://github.com/<owner>/<repo>/archive/<rev>.tar.gz"
    },
    "nixpkgs": {
        "branch": "nixpkgs-unstable",
        "description": "Nix Packages collection",
        "homepage": "",
        "owner": "NixOS",
        "repo": "nixpkgs",
        "rev": "5a5ac83292c7842072318f57d68a48474f8bd34d",
        "sha256": "0cdhkwq3nm0s1zyzbgl24whard7dgkq15425lapyaxklnjd65165",
        "type": "tarball",
        "url": "https://github.com/NixOS/nixpkgs/archive/5a5ac83292c7842072318f57d68a48474f8bd34d.tar.gz",
        "url_template": "https://github.com/<owner>/<repo>/archive/<rev>.tar.gz"
    },
    "nixpkgs-stable": {
        "branch": "release-23.11",
        "description": "Nix Packages collection",
        "homepage": "",
        "owner": "NixOS",
        "repo": "nixpkgs",
        "rev": "f88df4bf25b729d78712c441fb0910f7085e9395",
        "sha256": "14rdi6j2m47acc5rpzf42dw4259bdgsrcyhhy487dab5jrbqx376",
        "type": "tarball",
        "url": "https://github.com/NixOS/nixpkgs/archive/f88df4bf25b729d78712c441fb0910f7085e9395.tar.gz",
        "url_template": "https://github.com/<owner>/<repo>/archive/<rev>.tar.gz"
    }
}
